PyDaron/__init__.py
PyDaron/crypto.py
PyDaron/decrypto.py
PyDaron/module.py
PyDaron-0.0.1.dist-info/LICENSE
PyDaron-0.0.1.dist-info/METADATA
PyDaron-0.0.1.dist-info/WHEEL
PyDaron-0.0.1.dist-info/entry_points.txt
PyDaron-0.0.1.dist-info/top_level.txt
PyDaron-0.0.1.dist-info/RECORD
